highway_env/__init__.py
highway_env/interval.py
highway_env/utils.py
highway_env/envs/__init__.py
highway_env/envs/exit_env.py
highway_env/envs/highway_env.py
highway_env/envs/intersection_env.py
highway_env/envs/lane_keeping_env.py
highway_env/envs/merge_env.py
highway_env/envs/parking_env.py
highway_env/envs/racetrack_env.py
highway_env/envs/roundabout_env.py
highway_env/envs/two_way_env.py
highway_env/envs/u_turn_env.py
highway_env/envs/common/__init__.py
highway_env/envs/common/abstract.py
highway_env/envs/common/action.py
highway_env/envs/common/finite_mdp.py
highway_env/envs/common/graphics.py
highway_env/envs/common/observation.py
highway_env/road/__init__.py
highway_env/road/graphics.py
highway_env/road/lane.py
highway_env/road/regulation.py
highway_env/road/road.py
highway_env/road/spline.py
highway_env/vehicle/__init__.py
highway_env/vehicle/behavior.py
highway_env/vehicle/controller.py
highway_env/vehicle/dynamics.py
highway_env/vehicle/graphics.py
highway_env/vehicle/kinematics.py
highway_env/vehicle/objects.py
highway_env/vehicle/uncertainty/__init__.py
highway_env/vehicle/uncertainty/estimation.py
highway_env/vehicle/uncertainty/prediction.py
highway_env-1.10.1.dist-info/LICENSE
highway_env-1.10.1.dist-info/METADATA
highway_env-1.10.1.dist-info/WHEEL
highway_env-1.10.1.dist-info/top_level.txt
highway_env-1.10.1.dist-info/RECORD
