Metadata-Version: 2.1
Name: highway-env
Version: 1.10.1
Summary: An environment for simulated highway driving tasks.
Author-email: Edouard Leurent <eleurent@gmail.com>
License: MIT License
Project-URL: Homepage, https://farama.org
Project-URL: Repository, https://github.com/eleurent/highway-env
Project-URL: Documentation, https://highway-env.farama.org/
Project-URL: Bug Report, https://github.com/eleurent/highway-env/issues
Keywords: Reinforcement Learning,car simulation,RL,AI
Classifier: Development Status :: 5 - Production/Stable
Classifier: Programming Language :: Python :: 3
Classifier: Programming Language :: Python :: 3.8
Classifier: Programming Language :: Python :: 3.9
Classifier: Programming Language :: Python :: 3.10
Classifier: Programming Language :: Python :: 3.11
Classifier: Programming Language :: Python :: 3.12
Classifier: License :: OSI Approved :: MIT License
Classifier: Intended Audience :: Science/Research
Classifier: Topic :: Scientific/Engineering :: Artificial Intelligence
Requires-Python: >=3.8
License-File: LICENSE
Requires-Dist: gymnasium>=1.0.0a2
Requires-Dist: farama-notifications>=0.0.1
Requires-Dist: numpy>=1.21.0
Requires-Dist: pygame>=2.0.2
Requires-Dist: matplotlib
Requires-Dist: pandas
Requires-Dist: scipy
Provides-Extra: testing
Requires-Dist: pytest; extra == "testing"
Requires-Dist: pytest-cov; extra == "testing"
